odoo/addons/l10n_eu_product_adr_dangerous_goods/README.rst
odoo/addons/l10n_eu_product_adr_dangerous_goods/__init__.py
odoo/addons/l10n_eu_product_adr_dangerous_goods/__manifest__.py
odoo/addons/l10n_eu_product_adr_dangerous_goods/data/utility_models.xml
odoo/addons/l10n_eu_product_adr_dangerous_goods/i18n/es.po
odoo/addons/l10n_eu_product_adr_dangerous_goods/i18n/it.po
odoo/addons/l10n_eu_product_adr_dangerous_goods/i18n/l10n_eu_product_adr_dangerous_goods.pot
odoo/addons/l10n_eu_product_adr_dangerous_goods/models/__init__.py
odoo/addons/l10n_eu_product_adr_dangerous_goods/models/product_product.py
odoo/addons/l10n_eu_product_adr_dangerous_goods/models/utility_models.py
odoo/addons/l10n_eu_product_adr_dangerous_goods/readme/CONTRIBUTORS.rst
odoo/addons/l10n_eu_product_adr_dangerous_goods/readme/DESCRIPTION.rst
odoo/addons/l10n_eu_product_adr_dangerous_goods/readme/ROADMAP.rst
odoo/addons/l10n_eu_product_adr_dangerous_goods/security/ir.model.access.csv
odoo/addons/l10n_eu_product_adr_dangerous_goods/static/description/icon.png
odoo/addons/l10n_eu_product_adr_dangerous_goods/static/description/index.html
odoo/addons/l10n_eu_product_adr_dangerous_goods/views/product_product.xml
odoo14_addon_l10n_eu_product_adr_dangerous_goods-14.0.1.0.1.dev8.dist-info/METADATA
odoo14_addon_l10n_eu_product_adr_dangerous_goods-14.0.1.0.1.dev8.dist-info/WHEEL
odoo14_addon_l10n_eu_product_adr_dangerous_goods-14.0.1.0.1.dev8.dist-info/top_level.txt
odoo14_addon_l10n_eu_product_adr_dangerous_goods-14.0.1.0.1.dev8.dist-info/RECORD
