Metadata-Version: 2.1
Name: odoo14-addon-l10n_eu_product_adr_dangerous_goods
Version: 14.0.1.0.1.dev8
Summary: l10n Eu Product Adr Dangerous Goods
Home-page: https://github.com/OCA/community-data-files
Author: Camptocamp, Odoo Community Association (OCA)
Author-email: support@odoo-community.org
License: AGPL-3
Classifier: Programming Language :: Python
Classifier: Framework :: Odoo
Classifier: Framework :: Odoo :: 14.0
Classifier: License :: OSI Approved :: GNU Affero General Public License v3
Requires-Python: >=3.6
Requires-Dist: odoo14-addon-l10n-eu-product-adr
Requires-Dist: odoo<14.1dev,>=14.0a
